LICENSE
MANIFEST.in
README.rst
setup.py
dfuzz/__init__.py
dfuzz/__init__.pyc
dfuzz/dfuzz
dfuzz/incident_viewer
dfuzz.egg-info/PKG-INFO
dfuzz.egg-info/SOURCES.txt
dfuzz.egg-info/dependency_links.txt
dfuzz.egg-info/not-zip-safe
dfuzz.egg-info/top_level.txt
dfuzz/cfg/defaults.ini
dfuzz/comb/__init__.py
dfuzz/comb/simple.py
dfuzz/core/__init__.py
dfuzz/core/__init__.pyc
dfuzz/core/conf.py
dfuzz/core/conf.pyc
dfuzz/core/exceptions.py
dfuzz/core/exceptions.pyc
dfuzz/core/handler.py
dfuzz/core/incident.py
dfuzz/core/incident.pyc
dfuzz/core/loader.py
dfuzz/core/loader.pyc
dfuzz/core/runner.py
dfuzz/core/sanity.py
dfuzz/core/sanity.pyc
dfuzz/core/target.py
dfuzz/core/target.pyc
dfuzz/core/utils.py
dfuzz/core/utils.pyc
dfuzz/core/wrapper.py
dfuzz/core/wrapper.pyc
dfuzz/gen/__init__.py
dfuzz/gen/autodafe.py
dfuzz/mut/__init__.py
dfuzz/mut/plain.py
dfuzz/mut/zzuf.py
dfuzz/mut/zzuf_10.py
dfuzz/tests/__init__.py
dfuzz/tests/__init__.pyc
dfuzz/tests/test.py
dfuzz/tests/test.pyc
dfuzz/tests/test_conf.py
dfuzz/tests/test_conf.pyc
dfuzz/tests/test_incident.py
dfuzz/tests/test_incident.pyc
dfuzz/tests/test_loader.py
dfuzz/tests/test_loader.pyc
dfuzz/tests/test_sanity.py
dfuzz/tests/test_sanity.pyc
dfuzz/tests/test_utils.py
dfuzz/tests/test_utils.pyc
dfuzz/tests/dummy/__init__.py
dfuzz/tests/dummy/__init__.pyc
dfuzz/tests/dummy/complete_wrapper.py
dfuzz/tests/dummy/complete_wrapper.pyc
dfuzz/tests/dummy/incident_required.py
dfuzz/tests/dummy/incident_required.pyc
dfuzz/tests/dummy/incomplete_wrapper.py
dfuzz/tests/dummy/incomplete_wrapper.pyc
dfuzz/tests/dummy/invalid_wrapper.py
dfuzz/tests/dummy/invalid_wrapper.pyc
dfuzz/tests/dummy/sanity_cfg.py
dfuzz/tests/dummy/sanity_cfg.pyc
dfuzz/tests/dummy/sanity_cfg_validators.py
dfuzz/tests/dummy/sanity_cfg_validators.pyc
dfuzz/tests/dummy/standard_wrapper.py
dfuzz/tests/dummy/standard_wrapper.pyc
docs/README.html
docs/README.rst
docs/compile.sh
docs/parts/installation.rst
docs/parts/usage.rst
samples/cat_sample/README
samples/cat_sample/fuzz.conf
samples/cat_sample/mut/1
samples/ext_sample/README
samples/ext_sample/bo_sample.c
samples/ext_sample/fuzz.conf
