Metadata-Version: 1.0
Name: dfuzz
Version: 0.6
Summary: dfuzz - automated daemon fuzzer
Home-page: http://github.com/sorki/dfuzz
Author: Richard Marko
Author-email: rissko@gmail.com
License: UNKNOWN
Platform: UNKNOWN
Classifier: Development Status :: 4 - Beta
Classifier: Operating System :: OS Independent
Classifier: Intended Audience :: Developers
Classifier: Topic :: Software Development :: Testing
Classifier: Programming Language :: Python
